spid_cie_oidc/__init__.py
spid_cie_oidc/accounts/__init__.py
spid_cie_oidc/accounts/admin.py
spid_cie_oidc/accounts/admin_inlines.py
spid_cie_oidc/accounts/apps.py
spid_cie_oidc/accounts/models.py
spid_cie_oidc/accounts/migrations/0001_initial.py
spid_cie_oidc/accounts/migrations/0002_remove_user_taxpayer_id_user_attributes.py
spid_cie_oidc/accounts/migrations/0003_alter_user_attributes.py
spid_cie_oidc/accounts/migrations/__init__.py
spid_cie_oidc/accounts/templatetags/__init__.py
spid_cie_oidc/accounts/templatetags/has_group.py
spid_cie_oidc/authority/__init__.py
spid_cie_oidc/authority/admin.py
spid_cie_oidc/authority/apps.py
spid_cie_oidc/authority/models.py
spid_cie_oidc/authority/settings.py
spid_cie_oidc/authority/urls.py
spid_cie_oidc/authority/utils.py
spid_cie_oidc/authority/validators.py
spid_cie_oidc/authority/views.py
spid_cie_oidc/authority/migrations/0001_initial.py
spid_cie_oidc/authority/migrations/0002_alter_federationentityprofile_trust_mark_template.py
spid_cie_oidc/authority/migrations/0003_alter_federationdescendantcontact_entity_and_more.py
spid_cie_oidc/authority/migrations/0004_federationdescendant_jwks_and_more.py
spid_cie_oidc/authority/migrations/0005_alter_federationdescendant_jwks.py
spid_cie_oidc/authority/migrations/0006_stafftoken.py
spid_cie_oidc/authority/migrations/0007_stafftoken_expire_at.py
spid_cie_oidc/authority/migrations/0008_alter_stafftoken_token.py
spid_cie_oidc/authority/migrations/0009_delete_stafftoken.py
spid_cie_oidc/authority/migrations/0010_federationdescendant_metadata_and_more.py
spid_cie_oidc/authority/migrations/0011_federationdescendant_issue_x509_and_more.py
spid_cie_oidc/authority/migrations/0012_remove_federationdescendant_issue_x509.py
spid_cie_oidc/authority/migrations/0013_alter_federationdescendant_type_and_more.py
spid_cie_oidc/authority/migrations/__init__.py
spid_cie_oidc/authority/schemas/__init__.py
spid_cie_oidc/authority/schemas/advanced_entity_list_endpoint.py
spid_cie_oidc-1.4.5.dist-info/AUTHORS
spid_cie_oidc-1.4.5.dist-info/LICENSE
spid_cie_oidc-1.4.5.dist-info/METADATA
spid_cie_oidc-1.4.5.dist-info/WHEEL
spid_cie_oidc-1.4.5.dist-info/top_level.txt
spid_cie_oidc-1.4.5.dist-info/RECORD
