Metadata-Version: 2.1
Name: spid_cie_oidc
Version: 1.4.5
Summary: SPID/CIE OIDC Federation Entity
Home-page: https://github.com/peppelinux/spid-cie-oidc
Author: Giuseppe De Marco
Author-email: demarcog83@gmail.com
License: License :: OSI Approved :: Apache Software License
Classifier: Development Status :: 5 - Production/Stable
Classifier: License :: OSI Approved :: Apache Software License
Classifier: Programming Language :: Python :: 3.8
Classifier: Programming Language :: Python :: 3.9
Classifier: Programming Language :: Python :: 3.10
Classifier: Programming Language :: Python :: 3.11
Classifier: Topic :: Software Development :: Libraries :: Python Modules
License-File: LICENSE
License-File: AUTHORS
Requires-Dist: Django <5.0,>=4.0
Requires-Dist: cryptojwt >=1.8.2
Requires-Dist: pydantic <2.0,>=1.8.2
Requires-Dist: pytz >=2021.3
Requires-Dist: aiohttp <3.10,>3.9
Requires-Dist: requests <3.0,>=2.20
Requires-Dist: pydantic[email]
Requires-Dist: djagger
